README.rst
setup.py
oyb/__init__.py
oyb/anomaly.py
oyb/earth.py
oyb/rot.py
oyb.egg-info/PKG-INFO
oyb.egg-info/SOURCES.txt
oyb.egg-info/dependency_links.txt
oyb.egg-info/top_level.txt
oyb/tests/__init__.py
oyb/tests/anomaly.py
oyb/tests/earth.py
oyb/tests/orb.py
oyb/tests/rot.py