Metadata-Version: 2.1
Name: oyb
Version: 0.1.7
Summary: Oy vey! So many orbit models. Here's another one.
Home-page: https://github.com/Tythos/oyb
Author: Brian Kirkpatrick
Author-email: code@tythos.net
License: UNKNOWN
Platform: UNKNOWN
Classifier: Programming Language :: Python :: 3
Classifier: License :: OSI Approved :: MIT License
Classifier: Operating System :: OS Independent
